damage/__init__.py
damage/console/damage_cmd.py
damage/gui/assets/DamageAppIcon.icns
damage/gui/assets/DamageAppIcon.ico
damage/gui/assets/DamageAppIcon.jpg
damage/gui/assets/DamageAppIcon.png
damage/gui/assets/LICENCE.txt
damage/gui/damage_gui.py
damage-0.5.6.dist-info/LICENCE.md
damage-0.5.6.dist-info/METADATA
damage-0.5.6.dist-info/WHEEL
damage-0.5.6.dist-info/entry_points.txt
damage-0.5.6.dist-info/RECORD
